idempotency_header_middleware/__init__.py
idempotency_header_middleware/backends/__init__.py
idempotency_header_middleware/backends/base.py
idempotency_header_middleware/backends/memory.py
idempotency_header_middleware/backends/redis.py
idempotency_header_middleware/middleware.py
idempotency_header_middleware/py.typed
asgi_idempotency_header-0.2.0.dist-info/LICENSE
asgi_idempotency_header-0.2.0.dist-info/WHEEL
asgi_idempotency_header-0.2.0.dist-info/METADATA
asgi_idempotency_header-0.2.0.dist-info/RECORD
